LICENSE
MANIFEST.in
README.md
quicktest.py
settings_test.py
setup.py
django_odnoklassniki_api.egg-info/PKG-INFO
django_odnoklassniki_api.egg-info/SOURCES.txt
django_odnoklassniki_api.egg-info/dependency_links.txt
django_odnoklassniki_api.egg-info/not-zip-safe
django_odnoklassniki_api.egg-info/requires.txt
django_odnoklassniki_api.egg-info/top_level.txt
odnoklassniki_api/__init__.py
odnoklassniki_api/__init__.pyc
odnoklassniki_api/admin.py
odnoklassniki_api/admin.pyc
odnoklassniki_api/api.py
odnoklassniki_api/api.pyc
odnoklassniki_api/decorators.py
odnoklassniki_api/decorators.pyc
odnoklassniki_api/exceptions.py
odnoklassniki_api/exceptions.pyc
odnoklassniki_api/factories.py
odnoklassniki_api/fields.py
odnoklassniki_api/fields.pyc
odnoklassniki_api/fields_api.py
odnoklassniki_api/fields_api.pyc
odnoklassniki_api/models.py
odnoklassniki_api/models.pyc
odnoklassniki_api/tests.py
odnoklassniki_api/tests.pyc
odnoklassniki_api/utils.py
odnoklassniki_api/utils.pyc
odnoklassniki_api/widgets.py